{
  "hash": "fff922f3",
  "configHash": "bd96ed6d",
  "lockfileHash": "aff95f3a",
  "browserHash": "b3c1d57a",
  "optimized": {
    "react": {
      "src": "../../node_modules/react/index.js",
      "file": "react.js",
      "fileHash": "4bab172d",
      "needsInterop": true
    },
    "react-dom/client": {
      "src": "../../node_modules/react-dom/client.js",
      "file": "react-dom_client.js",
      "fileHash": "848a6b6a",
      "needsInterop": true
    },
    "react-router-dom": {
      "src": "../../node_modules/react-router-dom/dist/index.js",
      "file": "react-router-dom.js",
      "fileHash": "d8397a4e",
      "needsInterop": false
    },
    "classnames": {
      "src": "../../node_modules/classnames/index.js",
      "file": "classnames.js",
      "fileHash": "1d2232fc",
      "needsInterop": true
    }
  },
  "chunks": {
    "chunk-HCGKX5ED": {
      "file": "chunk-HCGKX5ED.js"
    },
    "chunk-WNPTCGAH": {
      "file": "chunk-WNPTCGAH.js"
    },
    "chunk-5WRI5ZAA": {
      "file": "chunk-5WRI5ZAA.js"
    }
  }
}